setup.py
gas/__init__.py
gas/__main__.py
gas/authorize.py
gas/base.py
gas/deploy.py
python_gas_cli.egg-info/PKG-INFO
python_gas_cli.egg-info/SOURCES.txt
python_gas_cli.egg-info/dependency_links.txt
python_gas_cli.egg-info/entry_points.txt
python_gas_cli.egg-info/not-zip-safe
python_gas_cli.egg-info/requires.txt
python_gas_cli.egg-info/top_level.txt